setup.cfg
setup.py
django_confirmation_mixin/__init__.py
django_confirmation_mixin/mixin.py
django_confirmation_mixin.egg-info/PKG-INFO
django_confirmation_mixin.egg-info/SOURCES.txt
django_confirmation_mixin.egg-info/dependency_links.txt
django_confirmation_mixin.egg-info/top_level.txt