Metadata-Version: 1.0
Name: django-confirmation-mixin
Version: 0.1.0
Summary: Django ConfirmationMixin for CreateView and UpdateView
Home-page: https://github.com/Sebubu/django-confirmation-mixin
Author: Severin Bühler
Author-email: sevi_buehler@hotmail.com
License: MIT
Keywords: django,django-mixin
Platform: UNKNOWN
